setup.py
distributions_frcc_udacity/Binomialdistribution.py
distributions_frcc_udacity/Gaussiandistribution.py
distributions_frcc_udacity/Generaldistribution.py
distributions_frcc_udacity/__init__.py
distributions_frcc_udacity.egg-info/PKG-INFO
distributions_frcc_udacity.egg-info/SOURCES.txt
distributions_frcc_udacity.egg-info/dependency_links.txt
distributions_frcc_udacity.egg-info/not-zip-safe
distributions_frcc_udacity.egg-info/top_level.txt