Metadata-Version: 1.0
Name: distributions-frcc-udacity
Version: 0.1
Summary: Gaussian distributions
Home-page: UNKNOWN
Author: Fernando Raul Cortez Chavez
Author-email: fernandoraulcc@gmail.com
License: UNKNOWN
Platform: UNKNOWN
